rackmail/__init__.py
rackmail/client.py
rackmail/main.py
rackmail/version.py
rackmail/subcommands/__init__.py
rackmail/subcommands/create_login_token.py
rackmail/subcommands/create_user.py
rackmail/subcommands/delete_user.py
rackmail/subcommands/disable_user.py
rackmail/subcommands/enable_user.py
rackmail/subcommands/get_mailbox.py
rackmail/subcommands/list_all.py
rackmail/subcommands/set_password.py
rackmail/subcommands/set_property.py
rackmail/utils/generate_random_string.py
rackmail/utils/output_json.py
rackmail-0.6.0.dist-info/METADATA
rackmail-0.6.0.dist-info/WHEEL
rackmail-0.6.0.dist-info/entry_points.txt
rackmail-0.6.0.dist-info/licenses/LICENSE
rackmail-0.6.0.dist-info/RECORD
