Metadata-Version: 2.4
Name: rackmail
Version: 0.6.0
Summary: CLI tool for managing Rackspace hosted mailboxes
Author-email: Zack Farmer <zackfarmer1710@gmail.com>
License: MIT License
License-File: LICENSE
Classifier: Development Status :: 4 - Beta
Classifier: Environment :: Console
Classifier: Intended Audience :: System Administrators
Classifier: License :: OSI Approved :: MIT License
Classifier: Operating System :: OS Independent
Classifier: Programming Language :: Python :: 3
Classifier: Topic :: Communications :: Email
Requires-Python: >=3.7
Requires-Dist: dotenv
Requires-Dist: requests
